{
  "required": true,
  "minVersion": "0.8",
  "package": "org.agmas.noellesroles.mixin",
  "compatibilityLevel": "JAVA_21",
  "mixins": [
    "BottomlessMixin",
    "DoNotCollideWithFeatherMixin",
    "GiveCoinsOnMoodCompletionMixin",
    "GunCooldownInject",
    "MixinItem",
    "PoisonerShopMixin",
    "bartender.BartenderPlayerShopComponentMixin",
    "bartender.BartenderReseterMixin",
    "bartender.CocktailItemMixin",
    "bartender.DefenseVialApplyMixin",
    "bartender.PoisonToHealsMixin",
    "bettervigilante.BetterVigilantePlayerShopComponentMixin",
    "coroner.CoronerAddDeathReasonMixin",
    "executioner.ExecutionerConfirmMixin",
    "executioner.ExecutionerGunPickupMixin",
    "executioner.NoTargetBackfireMixin",
    "fast2fast.AbilityCooldownComponent",
    "fast2fast.MixinAbilityPlayerComponent",
    "framing.DelusionVialApplyMixin",
    "framing.DoNotApplyFakePoisonMixin",
    "framing.FramingPassiveIncomeMixin",
    "framing.FramingRolesShopComponentMixin",
    "golden.GoldenPlayerShopComponentMixin",
    "host.MasterKeySmallDoorMixin",
    "host.MasterKeyTrainDoorMixin",
    "host.MoneyIncreaseMixin",
    "jester.FakeRevolverMixin",
    "jester.JesterItemEntityMixin",
    "jester.JesterJestMixin",
    "morphling.MorphlingReseterMixin",
    "noisemaker.NoisemakerKillMixin",
    "noisemaker.NoisemakerPlayerShopComponentMixin",
    "trapper.TrapperPlayerShopComponentMixin",
    "voodoo.VoodooShopComponentMixin",
    "voodoo.VoodooVooMixin"
  ],
  "injectors": {
    "defaultRequire": 1
  },
  "overwrites": {
    "requireAnnotations": true
  }
}